aiscraper/__init__.py
aiscraper/vanila_crawler/__init__.py
aiscraper/vanila_crawler/requests_handler.py
aiscraper/vanila_crawler/web_crawler.py
aiscraper-0.0.6.dist-info/LICENSE
aiscraper-0.0.6.dist-info/METADATA
aiscraper-0.0.6.dist-info/WHEEL
aiscraper-0.0.6.dist-info/top_level.txt
aiscraper-0.0.6.dist-info/RECORD
